vpex/_C.cpython-310-x86_64-linux-gnu.so
vpex/__init__.py
vpex/tc.py
vpex/lib/libvpex.so
vpex/lib/libvtal.so
vpex/testing/__init__.py
vpex/testing/utils.py
vpex/vtal/__init__.py
vpex/vtal/random.py
vpex/vtal/streams.py
vpex/vtal/utils.py
vpex.libs/libvpex-0587ca26.so
vpex.libs/libvtal-27b385c8.so
vpex-0.7.1.dist-info/METADATA
vpex-0.7.1.dist-info/WHEEL
vpex-0.7.1.dist-info/top_level.txt
vpex-0.7.1.dist-info/RECORD
